[
  {
    "name": "狼斥候",
    "src": "%E5%B0%8F%E5%A6%96-%E7%8B%BC%E6%96%A5%E5%80%99-%E5%BD%B1%E7%A5%9E%E5%9B%BE"
  },
  {
    "name": "狼剑客",
    "src": "%E5%B0%8F%E5%A6%96-%E7%8B%BC%E5%89%91%E5%AE%A2-%E5%BD%B1%E7%A5%9E%E5%9B%BE"
  },
  {
    "name": "狼校卫",
    "src": "%E5%B0%8F%E5%A6%96-%E7%8B%BC%E6%A0%A1%E5%8D%AB-%E5%BD%B1%E7%A5%9E%E5%9B%BE"
  },
  {
    "name": "狼力士",
    "src": "%E5%B0%8F%E5%A6%96-%E7%8B%BC%E5%8A%9B%E5%A3%AB-%E5%BD%B1%E7%A5%9E%E5%9B%BE"
  },
  {
    "name": "狼弓手",
    "src": "%E5%B0%8F%E5%A6%96-%E7%8B%BC%E5%BC%93%E6%89%8B-%E5%BD%B1%E7%A5%9E%E5%9B%BE"
  },
  {
    "name": "狼侍卫",
    "src": "%E5%B0%8F%E5%A6%96-%E7%8B%BC%E4%BE%8D%E5%8D%AB-%E5%BD%B1%E7%A5%9E%E5%9B%BE"
  },
  {
    "name": "狼刺客",
    "src": "%E5%B0%8F%E5%A6%96-%E7%8B%BC%E5%88%BA%E5%AE%A2-%E5%BD%B1%E7%A5%9E%E5%9B%BE"
  },
  {
    "name": "小呱呱",
    "src": "%E5%B0%8F%E5%A6%96-%E5%B0%8F%E5%91%B1%E5%91%B1-%E5%BD%B1%E7%A5%9E%E5%9B%BE"
  },
  {
    "name": "鸦香客",
    "src": "%E5%B0%8F%E5%A6%96-%E9%B8%A6%E9%A6%99%E5%AE%A2-%E5%BD%B1%E7%A5%9E%E5%9B%BE"
  },
  {
    "name": "山匪头子",
    "src": "%E5%B0%8F%E5%A6%96-%E5%B1%B1%E5%8C%AA%E5%A4%B4%E5%AD%90-%E5%BD%B1%E7%A5%9E%E5%9B%BE"
  },
  {
    "name": "骨嶙峋",
    "src": "%E5%B0%8F%E5%A6%96-%E9%AA%A8%E5%B6%99%E5%B3%8B-%E5%BD%B1%E7%A5%9E%E5%9B%BE"
  },
  {
    "name": "蛇巡司",
    "src": "%E5%B0%8F%E5%A6%96-%E8%9B%87%E5%B7%A1%E5%8F%B8-%E5%BD%B1%E7%A5%9E%E5%9B%BE"
  },
  {
    "name": "小菌君",
    "src": "%E5%B0%8F%E5%A6%96-%E5%B0%8F%E8%8F%8C%E5%90%9B-%E5%BD%B1%E7%A5%9E%E5%9B%BE"
  },
  {
    "name": "小人参精",
    "src": "%E5%B0%8F%E5%A6%96-%E5%B0%8F%E4%BA%BA%E5%8F%82%E7%B2%BE-%E5%BD%B1%E7%A5%9E%E5%9B%BE"
  },
  {
    "name": "鼠弩手",
    "src": "%E5%B0%8F%E5%A6%96-%E9%BC%A0%E5%BC%A9%E6%89%8B-%E5%BD%B1%E7%A5%9E%E5%9B%BE"
  },
  {
    "name": "鼠校卫",
    "src": "%E5%B0%8F%E5%A6%96-%E9%BC%A0%E6%A0%A1%E5%8D%AB-%E5%BD%B1%E7%A5%9E%E5%9B%BE"
  },
  {
    "name": "鼠司空",
    "src": "%E5%B0%8F%E5%A6%96-%E9%BC%A0%E5%8F%B8%E7%A9%BA-%E5%BD%B1%E7%A5%9E%E5%9B%BE"
  },
  {
    "name": "鼠都尉",
    "src": "%E5%B0%8F%E5%A6%96-%E9%BC%A0%E9%83%BD%E5%B0%89-%E5%BD%B1%E7%A5%9E%E5%9B%BE"
  },
  {
    "name": "鼠禁卫",
    "src": "%E5%B0%8F%E5%A6%96-%E9%BC%A0%E7%A6%81%E5%8D%AB-%E5%BD%B1%E7%A5%9E%E5%9B%BE"
  },
  {
    "name": "石磷磷",
    "src": "%E5%B0%8F%E5%A6%96-%E7%9F%B3%E7%A3%B7%E7%A3%B7-%E5%BD%B1%E7%A5%9E%E5%9B%BE"
  },
  {
    "name": "石苍苍",
    "src": "%E5%B0%8F%E5%A6%96-%E7%9F%B3%E8%8B%8D%E8%8B%8D-%E5%BD%B1%E7%A5%9E%E5%9B%BE"
  },
  {
    "name": "石双双",
    "src": "%E5%B0%8F%E5%A6%96-%E7%9F%B3%E5%8F%8C%E5%8F%8C-%E5%BD%B1%E7%A5%9E%E5%9B%BE"
  },
  {
    "name": "骨灵精",
    "src": "%E5%B0%8F%E5%A6%96-%E9%AA%A8%E7%81%B5%E7%B2%BE-%E5%BD%B1%E7%A5%9E%E5%9B%BE"
  },
  {
    "name": "骨悚然",
    "src": "%E5%B0%8F%E5%A6%96-%E9%AA%A8%E6%82%9A%E7%84%B6-%E5%BD%B1%E7%A5%9E%E5%9B%BE"
  },
  {
    "name": "疾蝠",
    "src": "%E5%B0%8F%E5%A6%96-%E7%96%BE%E8%9D%A0-%E5%BD%B1%E7%A5%9E%E5%9B%BE"
  },
  {
    "name": "干尸",
    "src": "%E5%B0%8F%E5%A6%96-%E5%B9%B2%E5%B0%B8-%E5%BD%B1%E7%A5%9E%E5%9B%BE"
  },
  {
    "name": "鼬侍郎",
    "src": "%E5%B0%8F%E5%A6%96-%E9%BC%AC%E4%BE%8D%E9%83%8E-%E5%BD%B1%E7%A5%9E%E5%9B%BE"
  },
  {
    "name": "狸侍长",
    "src": "%E5%B0%8F%E5%A6%96-%E7%8B%B8%E4%BE%8D%E9%95%BF-%E5%BD%B1%E7%A5%9E%E5%9B%BE"
  },
  {
    "name": "小灵芝精",
    "src": "%E5%B0%8F%E5%A6%96-%E5%B0%8F%E7%81%B5%E8%8A%9D%E7%B2%BE-%E5%BD%B1%E7%A5%9E%E5%9B%BE"
  },
  {
    "name": "支应僧",
    "src": "%E5%B0%8F%E5%A6%96-%E6%94%AF%E5%BA%94%E5%83%A7-%E5%BD%B1%E7%A5%9E%E5%9B%BE"
  },
  {
    "name": "戒刀僧",
    "src": "%E5%B0%8F%E5%A6%96-%E6%88%92%E5%88%80%E5%83%A7-%E5%BD%B1%E7%A5%9E%E5%9B%BE"
  },
  {
    "name": "提炉僧",
    "src": "%E5%B0%8F%E5%A6%96-%E6%8F%90%E7%82%89%E5%83%A7-%E5%BD%B1%E7%A5%9E%E5%9B%BE"
  },
  {
    "name": "迎客僧",
    "src": "%E5%B0%8F%E5%A6%96-%E8%BF%8E%E5%AE%A2%E5%83%A7-%E5%BD%B1%E7%A5%9E%E5%9B%BE"
  },
  {
    "name": "监院僧",
    "src": "%E5%B0%8F%E5%A6%96-%E7%9B%91%E9%99%A2%E5%83%A7-%E5%BD%B1%E7%A5%9E%E5%9B%BE"
  },
  {
    "name": "双刀僧",
    "src": "%E5%B0%8F%E5%A6%96-%E5%8F%8C%E5%88%80%E5%83%A7-%E5%BD%B1%E7%A5%9E%E5%9B%BE"
  },
  {
    "name": "青蝠",
    "src": "%E5%B0%8F%E5%A6%96-%E9%9D%92%E8%9D%A0-%E5%BD%B1%E7%A5%9E%E5%9B%BE"
  },
  {
    "name": "雪僵尸",
    "src": "%E5%B0%8F%E5%A6%96-%E9%9B%AA%E5%83%B5%E5%B0%B8-%E5%BD%B1%E7%A5%9E%E5%9B%BE"
  },
  {
    "name": "巡山鬼",
    "src": "%E5%B0%8F%E5%A6%96-%E5%B7%A1%E5%B1%B1%E9%AC%BC-%E5%BD%B1%E7%A5%9E%E5%9B%BE"
  },
  {
    "name": "穿云鬼",
    "src": "%E5%B0%8F%E5%A6%96-%E7%A9%BF%E4%BA%91%E9%AC%BC-%E5%BD%B1%E7%A5%9E%E5%9B%BE"
  },
  {
    "name": "冻饿鬼",
    "src": "%E5%B0%8F%E5%A6%96-%E5%86%BB%E9%A5%BF%E9%AC%BC-%E5%BD%B1%E7%A5%9E%E5%9B%BE"
  },
  {
    "name": "赤发鬼",
    "src": "%E5%B0%8F%E5%A6%96-%E8%B5%A4%E5%8F%91%E9%AC%BC-%E5%BD%B1%E7%A5%9E%E5%9B%BE"
  },
  {
    "name": "掌灯狱使",
    "src": "%E5%B0%8F%E5%A6%96-%E6%8E%8C%E7%81%AF%E7%8B%B1%E4%BD%BF-%E5%BD%B1%E7%A5%9E%E5%9B%BE"
  },
  {
    "name": "夜叉奴",
    "src": "%E5%B0%8F%E5%A6%96-%E5%A4%9C%E5%8F%89%E5%A5%B4-%E5%BD%B1%E7%A5%9E%E5%9B%BE"
  },
  {
    "name": "隼居士",
    "src": "%E5%B0%8F%E5%A6%96-%E9%9A%BC%E5%B1%85%E5%A3%AB-%E5%BD%B1%E7%A5%9E%E5%9B%BE"
  },
  {
    "name": "狼护法",
    "src": "%E5%B0%8F%E5%A6%96-%E7%8B%BC%E6%8A%A4%E6%B3%95-%E5%BD%B1%E7%A5%9E%E5%9B%BE"
  },
  {
    "name": "鳖宝",
    "src": "%E5%B0%8F%E5%A6%96-%E9%B3%96%E5%AE%9D-%E5%BD%B1%E7%A5%9E%E5%9B%BE"
  },
  {
    "name": "雷长老",
    "src": "%E5%B0%8F%E5%A6%96-%E9%9B%B7%E9%95%BF%E8%80%81-%E5%BD%B1%E7%A5%9E%E5%9B%BE"
  },
  {
    "name": "焦面鬼王",
    "src": "%E5%B0%8F%E5%A6%96-%E7%84%A6%E9%9D%A2%E9%AC%BC%E7%8E%8B-%E5%BD%B1%E7%A5%9E%E5%9B%BE"
  },
  {
    "name": "泥塑金刚",
    "src": "%E5%B0%8F%E5%A6%96-%E6%B3%A5%E5%A1%91%E9%87%91%E5%88%9A-%E5%BD%B1%E7%A5%9E%E5%9B%BE"
  },
  {
    "name": "地莲精",
    "src": "%E5%B0%8F%E5%A6%96-%E5%9C%B0%E8%8E%B2%E7%B2%BE-%E5%BD%B1%E7%A5%9E%E5%9B%BE"
  },
  {
    "name": "巫山小妖",
    "src": "%E5%B0%8F%E5%A6%96-%E5%B7%AB%E5%B1%B1%E5%B0%8F%E5%A6%96-%E5%BD%B1%E7%A5%9E%E5%9B%BE"
  },
  {
    "name": "傀蛛士",
    "src": "%E5%B0%8F%E5%A6%96-%E5%82%80%E8%9B%9B%E5%A3%AB-%E5%BD%B1%E7%A5%9E%E5%9B%BE"
  },
  {
    "name": "儡蜱士",
    "src": "%E5%B0%8F%E5%A6%96-%E5%84%A1%E8%9C%B1%E5%A3%AB-%E5%BD%B1%E7%A5%9E%E5%9B%BE"
  },
  {
    "name": "幽灯鬼",
    "src": "%E5%B0%8F%E5%A6%96-%E5%B9%BD%E7%81%AF%E9%AC%BC-%E5%BD%B1%E7%A5%9E%E5%9B%BE"
  },
  {
    "name": "蜢虫精",
    "src": "%E5%B0%8F%E5%A6%96-%E8%9C%A2%E8%99%AB%E7%B2%BE-%E5%BD%B1%E7%A5%9E%E5%9B%BE"
  },
  {
    "name": "蜻蜓精",
    "src": "%E5%B0%8F%E5%A6%96-%E8%9C%BB%E8%9C%93%E7%B2%BE-%E5%BD%B1%E7%A5%9E%E5%9B%BE"
  },
  {
    "name": "蚂蜂精",
    "src": "%E5%B0%8F%E5%A6%96-%E8%9A%82%E8%9C%82%E7%B2%BE-%E5%BD%B1%E7%A5%9E%E5%9B%BE"
  },
  {
    "name": "虫校尉",
    "src": "%E5%B0%8F%E5%A6%96-%E8%99%AB%E6%A0%A1%E5%B0%89-%E5%BD%B1%E7%A5%9E%E5%9B%BE"
  },
  {
    "name": "石蛛",
    "src": "%E5%B0%8F%E5%A6%96-%E7%9F%B3%E8%9B%9B-%E5%BD%B1%E7%A5%9E%E5%9B%BE"
  },
  {
    "name": "琴螂幼虫",
    "src": "%E5%B0%8F%E5%A6%96-%E7%90%B4%E8%9E%82%E5%B9%BC%E8%99%AB-%E5%BD%B1%E7%A5%9E%E5%9B%BE"
  },
  {
    "name": "利爪茧",
    "src": "%E5%B0%8F%E5%A6%96-%E5%88%A9%E7%88%AA%E8%8C%A7-%E5%BD%B1%E7%A5%9E%E5%9B%BE"
  },
  {
    "name": "蝎太子",
    "src": "%E5%B0%8F%E5%A6%96-%E8%9D%8E%E5%A4%AA%E5%AD%90-%E5%BD%B1%E7%A5%9E%E5%9B%BE"
  },
  {
    "name": "御剑道士",
    "src": "%E5%B0%8F%E5%A6%96-%E5%BE%A1%E5%89%91%E9%81%93%E5%A3%AB-%E5%BD%B1%E7%A5%9E%E5%9B%BE"
  },
  {
    "name": "拂尘道士",
    "src": "%E5%B0%8F%E5%A6%96-%E6%8B%82%E5%B0%98%E9%81%93%E5%A3%AB-%E5%BD%B1%E7%A5%9E%E5%9B%BE"
  },
  {
    "name": "执杖道士",
    "src": "%E5%B0%8F%E5%A6%96-%E6%89%A7%E6%9D%96%E9%81%93%E5%A3%AB-%E5%BD%B1%E7%A5%9E%E5%9B%BE"
  },
  {
    "name": "蛇司药",
    "src": "%E5%B0%8F%E5%A6%96-%E8%9B%87%E5%8F%B8%E8%8D%AF-%E5%BD%B1%E7%A5%9E%E5%9B%BE"
  },
  {
    "name": "蛇捕头",
    "src": "%E5%B0%8F%E5%A6%96-%E8%9B%87%E6%8D%95%E5%A4%B4-%E5%BD%B1%E7%A5%9E%E5%9B%BE"
  },
  {
    "name": "虫羽士",
    "src": "%E5%B0%8F%E5%A6%96-%E8%99%AB%E7%BE%BD%E5%A3%AB-%E5%BD%B1%E7%A5%9E%E5%9B%BE"
  },
  {
    "name": "青冉冉",
    "src": "%E5%B0%8F%E5%A6%96-%E9%9D%92%E5%86%89%E5%86%89-%E5%BD%B1%E7%A5%9E%E5%9B%BE"
  },
  {
    "name": "阴兵·力士",
    "src": "%E5%B0%8F%E5%A6%96-%E9%98%B4%E5%85%B5%C2%B7%E5%8A%9B%E5%A3%AB-%E5%BD%B1%E7%A5%9E%E5%9B%BE"
  },
  {
    "name": "阴兵·弓手",
    "src": "%E5%B0%8F%E5%A6%96-%E9%98%B4%E5%85%B5%C2%B7%E5%BC%93%E6%89%8B-%E5%BD%B1%E7%A5%9E%E5%9B%BE"
  },
  {
    "name": "阴兵·火牛",
    "src": "%E5%B0%8F%E5%A6%96-%E9%98%B4%E5%85%B5%C2%B7%E7%81%AB%E7%89%9B-%E5%BD%B1%E7%A5%9E%E5%9B%BE"
  },
  {
    "name": "阴兵·焦尸",
    "src": "%E5%B0%8F%E5%A6%96-%E9%98%B4%E5%85%B5%C2%B7%E7%84%A6%E5%B0%B8-%E5%BD%B1%E7%A5%9E%E5%9B%BE"
  },
  {
    "name": "阴兵·黑脸鬼",
    "src": "%E5%B0%8F%E5%A6%96-%E9%98%B4%E5%85%B5%C2%B7%E9%BB%91%E8%84%B8%E9%AC%BC-%E5%BD%B1%E7%A5%9E%E5%9B%BE"
  },
  {
    "name": "焰蝠",
    "src": "%E5%B0%8F%E5%A6%96-%E7%84%B0%E8%9D%A0-%E5%BD%B1%E7%A5%9E%E5%9B%BE"
  },
  {
    "name": "牛侍长",
    "src": "%E5%B0%8F%E5%A6%96-%E7%89%9B%E4%BE%8D%E9%95%BF-%E5%BD%B1%E7%A5%9E%E5%9B%BE"
  },
  {
    "name": "牛校卫",
    "src": "%E5%B0%8F%E5%A6%96-%E7%89%9B%E6%A0%A1%E5%8D%AB-%E5%BD%B1%E7%A5%9E%E5%9B%BE"
  },
  {
    "name": "牛力士",
    "src": "%E5%B0%8F%E5%A6%96-%E7%89%9B%E5%8A%9B%E5%A3%AB-%E5%BD%B1%E7%A5%9E%E5%9B%BE"
  },
  {
    "name": "火烈烈",
    "src": "%E5%B0%8F%E5%A6%96-%E7%81%AB%E7%83%88%E7%83%88-%E5%BD%B1%E7%A5%9E%E5%9B%BE"
  },
  {
    "name": "炎赫赫",
    "src": "%E5%B0%8F%E5%A6%96-%E7%82%8E%E8%B5%AB%E8%B5%AB-%E5%BD%B1%E7%A5%9E%E5%9B%BE"
  },
  {
    "name": "火灵童子",
    "src": "%E5%B0%8F%E5%A6%96-%E7%81%AB%E7%81%B5%E7%AB%A5%E5%AD%90-%E5%BD%B1%E7%A5%9E%E5%9B%BE"
  },
  {
    "name": "行什",
    "src": "%E5%B0%8F%E5%A6%96-%E8%A1%8C%E4%BB%80-%E5%BD%B1%E7%A5%9E%E5%9B%BE"
  },
  {
    "name": "地罗刹",
    "src": "%E5%B0%8F%E5%A6%96-%E5%9C%B0%E7%BD%97%E5%88%B9-%E5%BD%B1%E7%A5%9E%E5%9B%BE"
  },
  {
    "name": "海罗刹",
    "src": "%E5%B0%8F%E5%A6%96-%E6%B5%B7%E7%BD%97%E5%88%B9-%E5%BD%B1%E7%A5%9E%E5%9B%BE"
  },
  {
    "name": "火长老",
    "src": "%E5%B0%8F%E5%A6%96-%E7%81%AB%E9%95%BF%E8%80%81-%E5%BD%B1%E7%A5%9E%E5%9B%BE"
  },
  {
    "name": "牯都督",
    "src": "%E5%B0%8F%E5%A6%96-%E7%89%AF%E9%83%BD%E7%9D%A3-%E5%BD%B1%E7%A5%9E%E5%9B%BE"
  },
  {
    "name": "鹰天兵",
    "src": "%E5%B0%8F%E5%A6%96-%E9%B9%B0%E5%A4%A9%E5%85%B5-%E5%BD%B1%E7%A5%9E%E5%9B%BE"
  },
  {
    "name": "犬天兵",
    "src": "%E5%B0%8F%E5%A6%96-%E7%8A%AC%E5%A4%A9%E5%85%B5-%E5%BD%B1%E7%A5%9E%E5%9B%BE"
  },
  {
    "name": "豺天兵",
    "src": "%E5%B0%8F%E5%A6%96-%E8%B1%BA%E5%A4%A9%E5%85%B5-%E5%BD%B1%E7%A5%9E%E5%9B%BE"
  },
  {
    "name": "天将",
    "src": "%E5%B0%8F%E5%A6%96-%E5%A4%A9%E5%B0%86-%E5%BD%B1%E7%A5%9E%E5%9B%BE"
  },
  {
    "name": "牯护院",
    "src": "%E5%A4%B4%E7%9B%AE-%E7%89%AF%E6%8A%A4%E9%99%A2-%E5%BD%B1%E7%A5%9E%E5%9B%BE"
  },
  {
    "name": "广智",
    "src": "%E5%A4%B4%E7%9B%AE-%E5%B9%BF%E6%99%BA-%E5%BD%B1%E7%A5%9E%E5%9B%BE"
  },
  {
    "name": "广谋",
    "src": "%E5%A4%B4%E7%9B%AE-%E5%B9%BF%E8%B0%8B-%E5%BD%B1%E7%A5%9E%E5%9B%BE"
  },
  {
    "name": "波里个浪",
    "src": "%E5%A4%B4%E7%9B%AE-%E6%B3%A2%E9%87%8C%E4%B8%AA%E6%B5%AA-%E5%BD%B1%E7%A5%9E%E5%9B%BE"
  },
  {
    "name": "浪里个波",
    "src": "%E5%A4%B4%E7%9B%AE-%E6%B5%AA%E9%87%8C%E4%B8%AA%E6%B3%A2-%E5%BD%B1%E7%A5%9E%E5%9B%BE"
  },
  {
    "name": "地狼",
    "src": "%E5%A4%B4%E7%9B%AE-%E5%9C%B0%E7%8B%BC-%E5%BD%B1%E7%A5%9E%E5%9B%BE"
  },
  {
    "name": "沙国王父子",
    "src": "%E5%A4%B4%E7%9B%AE-%E6%B2%99%E5%9B%BD%E7%8E%8B%E7%88%B6%E5%AD%90-%E5%BD%B1%E7%A5%9E%E5%9B%BE"
  },
  {
    "name": "沙大郎",
    "src": "%E5%A4%B4%E7%9B%AE-%E6%B2%99%E5%A4%A7%E9%83%8E-%E5%BD%B1%E7%A5%9E%E5%9B%BE"
  },
  {
    "name": "石母",
    "src": "%E5%A4%B4%E7%9B%AE-%E7%9F%B3%E6%AF%8D-%E5%BD%B1%E7%A5%9E%E5%9B%BE"
  },
  {
    "name": "虎伥",
    "src": "%E5%A4%B4%E7%9B%AE-%E8%99%8E%E4%BC%A5-%E5%BD%B1%E7%A5%9E%E5%9B%BE"
  },
  {
    "name": "百目真人",
    "src": "%E5%A4%B4%E7%9B%AE-%E7%99%BE%E7%9B%AE%E7%9C%9F%E4%BA%BA-%E5%BD%B1%E7%A5%9E%E5%9B%BE"
  },
  {
    "name": "疯虎",
    "src": "%E5%A4%B4%E7%9B%AE-%E7%96%AF%E8%99%8E-%E5%BD%B1%E7%A5%9E%E5%9B%BE"
  },
  {
    "name": "“虎先锋”",
    "src": "%E5%A4%B4%E7%9B%AE-%E2%80%9C%E8%99%8E%E5%85%88%E9%94%8B%E2%80%9D-%E5%BD%B1%E7%A5%9E%E5%9B%BE"
  },
  {
    "name": "魔将·莲眼",
    "src": "%E5%A4%B4%E7%9B%AE-%E9%AD%94%E5%B0%86%C2%B7%E8%8E%B2%E7%9C%BC-%E5%BD%B1%E7%A5%9E%E5%9B%BE"
  },
  {
    "name": "魔将·妄相",
    "src": "%E5%A4%B4%E7%9B%AE-%E9%AD%94%E5%B0%86%C2%B7%E5%A6%84%E7%9B%B8-%E5%BD%B1%E7%A5%9E%E5%9B%BE"
  },
  {
    "name": "魔将·劫波",
    "src": "%E5%A4%B4%E7%9B%AE-%E9%AD%94%E5%B0%86%C2%B7%E5%8A%AB%E6%B3%A2-%E5%BD%B1%E7%A5%9E%E5%9B%BE"
  },
  {
    "name": "无量蝠",
    "src": "%E5%A4%B4%E7%9B%AE-%E6%97%A0%E9%87%8F%E8%9D%A0-%E5%BD%B1%E7%A5%9E%E5%9B%BE"
  },
  {
    "name": "浪里个浪",
    "src": "%E5%A4%B4%E7%9B%AE-%E6%B5%AA%E9%87%8C%E4%B8%AA%E6%B5%AA-%E5%BD%B1%E7%A5%9E%E5%9B%BE"
  },
  {
    "name": "老人参精",
    "src": "%E5%A4%B4%E7%9B%AE-%E8%80%81%E4%BA%BA%E5%8F%82%E7%B2%BE-%E5%BD%B1%E7%A5%9E%E5%9B%BE"
  },
  {
    "name": "不白",
    "src": "%E5%A4%B4%E7%9B%AE-%E4%B8%8D%E7%99%BD-%E5%BD%B1%E7%A5%9E%E5%9B%BE"
  },
  {
    "name": "不净",
    "src": "%E5%A4%B4%E7%9B%AE-%E4%B8%8D%E5%87%80-%E5%BD%B1%E7%A5%9E%E5%9B%BE"
  },
  {
    "name": "不能",
    "src": "%E5%A4%B4%E7%9B%AE-%E4%B8%8D%E8%83%BD-%E5%BD%B1%E7%A5%9E%E5%9B%BE"
  },
  {
    "name": "不空",
    "src": "%E5%A4%B4%E7%9B%AE-%E4%B8%8D%E7%A9%BA-%E5%BD%B1%E7%A5%9E%E5%9B%BE"
  },
  {
    "name": "海上僧",
    "src": "%E5%A4%B4%E7%9B%AE-%E6%B5%B7%E4%B8%8A%E5%83%A7-%E5%BD%B1%E7%A5%9E%E5%9B%BE"
  },
  {
    "name": "赤尻马猴",
    "src": "%E5%A4%B4%E7%9B%AE-%E8%B5%A4%E5%B0%BB%E9%A9%AC%E7%8C%B4-%E5%BD%B1%E7%A5%9E%E5%9B%BE"
  },
  {
    "name": "六妹",
    "src": "%E5%A4%B4%E7%9B%AE-%E5%85%AD%E5%A6%B9-%E5%BD%B1%E7%A5%9E%E5%9B%BE"
  },
  {
    "name": "五妹",
    "src": "%E5%A4%B4%E7%9B%AE-%E4%BA%94%E5%A6%B9-%E5%BD%B1%E7%A5%9E%E5%9B%BE"
  },
  {
    "name": "四姐",
    "src": "%E5%A4%B4%E7%9B%AE-%E5%9B%9B%E5%A7%90-%E5%BD%B1%E7%A5%9E%E5%9B%BE"
  },
  {
    "name": "三姐",
    "src": "%E5%A4%B4%E7%9B%AE-%E4%B8%89%E5%A7%90-%E5%BD%B1%E7%A5%9E%E5%9B%BE"
  },
  {
    "name": "二姐",
    "src": "%E5%A4%B4%E7%9B%AE-%E4%BA%8C%E5%A7%90-%E5%BD%B1%E7%A5%9E%E5%9B%BE"
  },
  {
    "name": "大姐",
    "src": "%E5%A4%B4%E7%9B%AE-%E5%A4%A7%E5%A7%90-%E5%BD%B1%E7%A5%9E%E5%9B%BE"
  },
  {
    "name": "琴螂仙",
    "src": "%E5%A4%B4%E7%9B%AE-%E7%90%B4%E8%9E%82%E4%BB%99-%E5%BD%B1%E7%A5%9E%E5%9B%BE"
  },
  {
    "name": "百足虫",
    "src": "%E5%A4%B4%E7%9B%AE-%E7%99%BE%E8%B6%B3%E8%99%AB-%E5%BD%B1%E7%A5%9E%E5%9B%BE"
  },
  {
    "name": "右手虫",
    "src": "%E5%A4%B4%E7%9B%AE-%E5%8F%B3%E6%89%8B%E8%99%AB-%E5%BD%B1%E7%A5%9E%E5%9B%BE"
  },
  {
    "name": "波里个波",
    "src": "%E5%A4%B4%E7%9B%AE-%E6%B3%A2%E9%87%8C%E4%B8%AA%E6%B3%A2-%E5%BD%B1%E7%A5%9E%E5%9B%BE"
  },
  {
    "name": "虫总兵",
    "src": "%E5%A4%B4%E7%9B%AE-%E8%99%AB%E6%80%BB%E5%85%B5-%E5%BD%B1%E7%A5%9E%E5%9B%BE"
  },
  {
    "name": "靡道人",
    "src": "%E5%A4%B4%E7%9B%AE-%E9%9D%A1%E9%81%93%E4%BA%BA-%E5%BD%B1%E7%A5%9E%E5%9B%BE"
  },
  {
    "name": "五行战车",
    "src": "%E5%A4%B4%E7%9B%AE-%E4%BA%94%E8%A1%8C%E6%88%98%E8%BD%A6-%E5%BD%B1%E7%A5%9E%E5%9B%BE"
  },
  {
    "name": "石父",
    "src": "%E5%A4%B4%E7%9B%AE-%E7%9F%B3%E7%88%B6-%E5%BD%B1%E7%A5%9E%E5%9B%BE"
  },
  {
    "name": "急如火、快如风",
    "src": "%E5%A4%B4%E7%9B%AE-%E6%80%A5%E5%A6%82%E7%81%AB%E3%80%81%E5%BF%AB%E5%A6%82%E9%A3%8E-%E5%BD%B1%E7%A5%9E%E5%9B%BE"
  },
  {
    "name": "云里雾、雾里云",
    "src": "%E5%A4%B4%E7%9B%AE-%E4%BA%91%E9%87%8C%E9%9B%BE%E3%80%81%E9%9B%BE%E9%87%8C%E4%BA%91-%E5%BD%B1%E7%A5%9E%E5%9B%BE"
  },
  {
    "name": "兴烘掀、掀烘兴",
    "src": "%E5%A4%B4%E7%9B%AE-%E5%85%B4%E7%83%98%E6%8E%80%E3%80%81%E6%8E%80%E7%83%98%E5%85%B4-%E5%BD%B1%E7%A5%9E%E5%9B%BE"
  },
  {
    "name": "燧统领",
    "src": "%E5%A4%B4%E7%9B%AE-%E7%87%A7%E7%BB%9F%E9%A2%86-%E5%BD%B1%E7%A5%9E%E5%9B%BE"
  },
  {
    "name": "燧先锋",
    "src": "%E5%A4%B4%E7%9B%AE-%E7%87%A7%E5%85%88%E9%94%8B-%E5%BD%B1%E7%A5%9E%E5%9B%BE"
  },
  {
    "name": "火灵元母",
    "src": "%E5%A4%B4%E7%9B%AE-%E7%81%AB%E7%81%B5%E5%85%83%E6%AF%8D-%E5%BD%B1%E7%A5%9E%E5%9B%BE"
  },
  {
    "name": "波浪浪",
    "src": "%E5%A4%B4%E7%9B%AE-%E6%B3%A2%E6%B5%AA%E6%B5%AA-%E5%BD%B1%E7%A5%9E%E5%9B%BE"
  },
  {
    "name": "石子",
    "src": "%E5%A4%B4%E7%9B%AE-%E7%9F%B3%E5%AD%90-%E5%BD%B1%E7%A5%9E%E5%9B%BE"
  },
  {
    "name": "毒统领",
    "src": "%E5%A4%B4%E7%9B%AE-%E6%AF%92%E7%BB%9F%E9%A2%86-%E5%BD%B1%E7%A5%9E%E5%9B%BE"
  },
  {
    "name": "水木兽",
    "src": "%E5%A4%B4%E7%9B%AE-%E6%B0%B4%E6%9C%A8%E5%85%BD-%E5%BD%B1%E7%A5%9E%E5%9B%BE"
  },
  {
    "name": "跳浪蛟",
    "src": "%E5%A4%B4%E7%9B%AE-%E8%B7%B3%E6%B5%AA%E8%9B%9F-%E5%BD%B1%E7%A5%9E%E5%9B%BE"
  },
  {
    "name": "浪波波",
    "src": "%E5%A4%B4%E7%9B%AE-%E6%B5%AA%E6%B3%A2%E6%B3%A2-%E5%BD%B1%E7%A5%9E%E5%9B%BE"
  },
  {
    "name": "金甲犀",
    "src": "%E5%A4%B4%E7%9B%AE-%E9%87%91%E7%94%B2%E7%8A%80-%E5%BD%B1%E7%A5%9E%E5%9B%BE"
  },
  {
    "name": "步云鹿",
    "src": "%E5%A4%B4%E7%9B%AE-%E6%AD%A5%E4%BA%91%E9%B9%BF-%E5%BD%B1%E7%A5%9E%E5%9B%BE"
  },
  {
    "name": "凤翅将军",
    "src": "%E5%A4%B4%E7%9B%AE-%E5%87%A4%E7%BF%85%E5%B0%86%E5%86%9B-%E5%BD%B1%E7%A5%9E%E5%9B%BE"
  },
  {
    "name": "碧臂螂",
    "src": "%E5%A4%B4%E7%9B%AE-%E7%A2%A7%E8%87%82%E8%9E%82-%E5%BD%B1%E7%A5%9E%E5%9B%BE"
  },
  {
    "name": "灵虚子",
    "src": "%E5%A6%96%E7%8E%8B-%E7%81%B5%E8%99%9A%E5%AD%90-%E5%BD%B1%E7%A5%9E%E5%9B%BE"
  },
  {
    "name": "赤髯龙",
    "src": "%E5%A6%96%E7%8E%8B-%E8%B5%A4%E9%AB%AF%E9%BE%99-%E5%BD%B1%E7%A5%9E%E5%9B%BE"
  },
  {
    "name": "金池长老",
    "src": "%E5%A6%96%E7%8E%8B-%E9%87%91%E6%B1%A0%E9%95%BF%E8%80%81-%E5%BD%B1%E7%A5%9E%E5%9B%BE"
  },
  {
    "name": "黑风大王",
    "src": "%E5%A6%96%E7%8E%8B-%E9%BB%91%E9%A3%8E%E5%A4%A7%E7%8E%8B-%E5%BD%B1%E7%A5%9E%E5%9B%BE"
  },
  {
    "name": "黑熊精",
    "src": "%E5%A6%96%E7%8E%8B-%E9%BB%91%E7%86%8A%E7%B2%BE-%E5%BD%B1%E7%A5%9E%E5%9B%BE"
  },
  {
    "name": "虎先锋",
    "src": "%E5%A6%96%E7%8E%8B-%E8%99%8E%E5%85%88%E9%94%8B-%E5%BD%B1%E7%A5%9E%E5%9B%BE"
  },
  {
    "name": "石先锋",
    "src": "%E5%A6%96%E7%8E%8B-%E7%9F%B3%E5%85%88%E9%94%8B-%E5%BD%B1%E7%A5%9E%E5%9B%BE"
  },
  {
    "name": "石敢当",
    "src": "%E5%A6%96%E7%8E%8B-%E7%9F%B3%E6%95%A2%E5%BD%93-%E5%BD%B1%E7%A5%9E%E5%9B%BE"
  },
  {
    "name": "小骊龙",
    "src": "%E5%A6%96%E7%8E%8B-%E5%B0%8F%E9%AA%8A%E9%BE%99-%E5%BD%B1%E7%A5%9E%E5%9B%BE"
  },
  {
    "name": "蝜蝂",
    "src": "%E5%A6%96%E7%8E%8B-%E8%9D%9C%E8%9D%82-%E5%BD%B1%E7%A5%9E%E5%9B%BE"
  },
  {
    "name": "黄风大圣",
    "src": "%E5%A6%96%E7%8E%8B-%E9%BB%84%E9%A3%8E%E5%A4%A7%E5%9C%A3-%E5%BD%B1%E7%A5%9E%E5%9B%BE"
  },
  {
    "name": "亢金龙",
    "src": "%E5%A6%96%E7%8E%8B-%E4%BA%A2%E9%87%91%E9%BE%99-%E5%BD%B1%E7%A5%9E%E5%9B%BE"
  },
  {
    "name": "亢金星君",
    "src": "%E5%A6%96%E7%8E%8B-%E4%BA%A2%E9%87%91%E6%98%9F%E5%90%9B-%E5%BD%B1%E7%A5%9E%E5%9B%BE"
  },
  {
    "name": "魔将·妙音",
    "src": "%E5%A6%96%E7%8E%8B-%E9%AD%94%E5%B0%86%C2%B7%E5%A6%99%E9%9F%B3-%E5%BD%B1%E7%A5%9E%E5%9B%BE"
  },
  {
    "name": "青背龙",
    "src": "%E5%A6%96%E7%8E%8B-%E9%9D%92%E8%83%8C%E9%BE%99-%E5%BD%B1%E7%A5%9E%E5%9B%BE"
  },
  {
    "name": "黄眉",
    "src": "%E5%A6%96%E7%8E%8B-%E9%BB%84%E7%9C%89-%E5%BD%B1%E7%A5%9E%E5%9B%BE"
  },
  {
    "name": "紫蛛儿",
    "src": "%E5%A6%96%E7%8E%8B-%E7%B4%AB%E8%9B%9B%E5%84%BF-%E5%BD%B1%E7%A5%9E%E5%9B%BE"
  },
  {
    "name": "小黄龙",
    "src": "%E5%A6%96%E7%8E%8B-%E5%B0%8F%E9%BB%84%E9%BE%99-%E5%BD%B1%E7%A5%9E%E5%9B%BE"
  },
  {
    "name": "毒敌大王",
    "src": "%E5%A6%96%E7%8E%8B-%E6%AF%92%E6%95%8C%E5%A4%A7%E7%8E%8B-%E5%BD%B1%E7%A5%9E%E5%9B%BE"
  },
  {
    "name": "晦月魔君",
    "src": "%E5%A6%96%E7%8E%8B-%E6%99%A6%E6%9C%88%E9%AD%94%E5%90%9B-%E5%BD%B1%E7%A5%9E%E5%9B%BE"
  },
  {
    "name": "百眼魔君",
    "src": "%E5%A6%96%E7%8E%8B-%E7%99%BE%E7%9C%BC%E9%AD%94%E5%90%9B-%E5%BD%B1%E7%A5%9E%E5%9B%BE"
  },
  {
    "name": "阴阳鱼",
    "src": "%E5%A6%96%E7%8E%8B-%E9%98%B4%E9%98%B3%E9%B1%BC-%E5%BD%B1%E7%A5%9E%E5%9B%BE"
  },
  {
    "name": "璧水金睛兽",
    "src": "%E5%A6%96%E7%8E%8B-%E7%92%A7%E6%B0%B4%E9%87%91%E7%9D%9B%E5%85%BD-%E5%BD%B1%E7%A5%9E%E5%9B%BE"
  },
  {
    "name": "红孩儿",
    "src": "%E5%A6%96%E7%8E%8B-%E7%BA%A2%E5%AD%A9%E5%84%BF-%E5%BD%B1%E7%A5%9E%E5%9B%BE"
  },
  {
    "name": "夜叉王",
    "src": "%E5%A6%96%E7%8E%8B-%E5%A4%9C%E5%8F%89%E7%8E%8B-%E5%BD%B1%E7%A5%9E%E5%9B%BE"
  },
  {
    "name": "大石敢当",
    "src": "%E5%A6%96%E7%8E%8B-%E5%A4%A7%E7%9F%B3%E6%95%A2%E5%BD%93-%E5%BD%B1%E7%A5%9E%E5%9B%BE"
  },
  {
    "name": "红依",
    "src": "%E4%BA%BA%E7%89%A9-%E7%BA%A2%E4%BE%9D-%E5%BD%B1%E7%A5%9E%E5%9B%BE"
  },
  {
    "name": "袁守诚",
    "src": "%E4%BA%BA%E7%89%A9-%E8%A2%81%E5%AE%88%E8%AF%9A-%E5%BD%B1%E7%A5%9E%E5%9B%BE"
  },
  {
    "name": "猪八戒",
    "src": "%E4%BA%BA%E7%89%A9-%E7%8C%AA%E5%85%AB%E6%88%92-%E5%BD%B1%E7%A5%9E%E5%9B%BE"
  },
  {
    "name": "寅虎",
    "src": "%E4%BA%BA%E7%89%A9-%E5%AF%85%E8%99%8E-%E5%BD%B1%E7%A5%9E%E5%9B%BE"
  },
  {
    "name": "铁扇公主",
    "src": "%E4%BA%BA%E7%89%A9-%E9%93%81%E6%89%87%E5%85%AC%E4%B8%BB-%E5%BD%B1%E7%A5%9E%E5%9B%BE"
  },
  {
    "name": "通臂猿猴",
    "src": "%E4%BA%BA%E7%89%A9-%E9%80%9A%E8%87%82%E7%8C%BF%E7%8C%B4-%E5%BD%B1%E7%A5%9E%E5%9B%BE"
  },
  {
    "name": "萍萍",
    "src": "%E4%BA%BA%E7%89%A9-%E8%90%8D%E8%90%8D-%E5%BD%B1%E7%A5%9E%E5%9B%BE"
  },
  {
    "name": "石中人",
    "src": "%E4%BA%BA%E7%89%A9-%E7%9F%B3%E4%B8%AD%E4%BA%BA-%E5%BD%B1%E7%A5%9E%E5%9B%BE"
  },
  {
    "name": "申猴",
    "src": "%E4%BA%BA%E7%89%A9-%E7%94%B3%E7%8C%B4-%E5%BD%B1%E7%A5%9E%E5%9B%BE"
  },
  {
    "name": "王灵官",
    "src": "%E4%BA%BA%E7%89%A9-%E7%8E%8B%E7%81%B5%E5%AE%98-%E5%BD%B1%E7%A5%9E%E5%9B%BE"
  },
  {
    "name": "牛魔王",
    "src": "%E4%BA%BA%E7%89%A9-%E7%89%9B%E9%AD%94%E7%8E%8B-%E5%BD%B1%E7%A5%9E%E5%9B%BE"
  },
  {
    "name": "无头僧",
    "src": "%E4%BA%BA%E7%89%A9-%E6%97%A0%E5%A4%B4%E5%83%A7-%E5%BD%B1%E7%A5%9E%E5%9B%BE"
  },
  {
    "name": "戌狗",
    "src": "%E4%BA%BA%E7%89%A9-%E6%88%8C%E7%8B%97-%E5%BD%B1%E7%A5%9E%E5%9B%BE"
  },
  {
    "name": "小西天土地",
    "src": "%E4%BA%BA%E7%89%A9-%E5%B0%8F%E8%A5%BF%E5%A4%A9%E5%9C%9F%E5%9C%B0-%E5%BD%B1%E7%A5%9E%E5%9B%BE"
  },
  {
    "name": "小张太子",
    "src": "%E4%BA%BA%E7%89%A9-%E5%B0%8F%E5%BC%A0%E5%A4%AA%E5%AD%90-%E5%BD%B1%E7%A5%9E%E5%9B%BE"
  },
  {
    "name": "龟将",
    "src": "%E4%BA%BA%E7%89%A9-%E9%BE%9F%E5%B0%86-%E5%BD%B1%E7%A5%9E%E5%9B%BE"
  },
  {
    "name": "黑风山土地",
    "src": "%E4%BA%BA%E7%89%A9-%E9%BB%91%E9%A3%8E%E5%B1%B1%E5%9C%9F%E5%9C%B0-%E5%BD%B1%E7%A5%9E%E5%9B%BE"
  },
  {
    "name": "黑手道人",
    "src": "%E4%BA%BA%E7%89%A9-%E9%BB%91%E6%89%8B%E9%81%93%E4%BA%BA-%E5%BD%B1%E7%A5%9E%E5%9B%BE"
  },
  {
    "name": "黄袍员外",
    "src": "%E4%BA%BA%E7%89%A9-%E9%BB%84%E8%A2%8D%E5%91%98%E5%A4%96-%E5%BD%B1%E7%A5%9E%E5%9B%BE"
  },
  {
    "name": "鹤仙人",
    "src": "%E4%BA%BA%E7%89%A9-%E9%B9%A4%E4%BB%99%E4%BA%BA-%E5%BD%B1%E7%A5%9E%E5%9B%BE"
  },
  {
    "name": "马天霸",
    "src": "%E4%BA%BA%E7%89%A9-%E9%A9%AC%E5%A4%A9%E9%9C%B8-%E5%BD%B1%E7%A5%9E%E5%9B%BE"
  },
  {
    "name": "老猴子",
    "src": "%E4%BA%BA%E7%89%A9-%E8%80%81%E7%8C%B4%E5%AD%90-%E5%BD%B1%E7%A5%9E%E5%9B%BE"
  },
  {
    "name": "皓斧力士",
    "src": "%E4%BA%BA%E7%89%A9-%E7%9A%93%E6%96%A7%E5%8A%9B%E5%A3%AB-%E5%BD%B1%E7%A5%9E%E5%9B%BE"
  },
  {
    "name": "灵狐",
    "src": "%E4%BA%BA%E7%89%A9-%E7%81%B5%E7%8B%90-%E5%BD%B1%E7%A5%9E%E5%9B%BE"
  },
  {
    "name": "灵吉菩萨",
    "src": "%E4%BA%BA%E7%89%A9-%E7%81%B5%E5%90%89%E8%8F%A9%E8%90%A8-%E5%BD%B1%E7%A5%9E%E5%9B%BE"
  },
  {
    "name": "火焰山土地",
    "src": "%E4%BA%BA%E7%89%A9-%E7%81%AB%E7%84%B0%E5%B1%B1%E5%9C%9F%E5%9C%B0-%E5%BD%B1%E7%A5%9E%E5%9B%BE"
  },
  {
    "name": "弥勒",
    "src": "%E4%BA%BA%E7%89%A9-%E5%BC%A5%E5%8B%92-%E5%BD%B1%E7%A5%9E%E5%9B%BE"
  },
  {
    "name": "二郎显圣真君",
    "src": "%E4%BA%BA%E7%89%A9-%E4%BA%8C%E9%83%8E%E6%98%BE%E5%9C%A3%E7%9C%9F%E5%90%9B-%E5%BD%B1%E7%A5%9E%E5%9B%BE"
  },
  {
    "name": "辰龙",
    "src": "%E4%BA%BA%E7%89%A9-%E8%BE%B0%E9%BE%99-%E5%BD%B1%E7%A5%9E%E5%9B%BE"
  },
  {
    "name": "翠笠武师",
    "src": "%E4%BA%BA%E7%89%A9-%E7%BF%A0%E7%AC%A0%E6%AD%A6%E5%B8%88-%E5%BD%B1%E7%A5%9E%E5%9B%BE"
  },
  {
    "name": "白衣秀士",
    "src": "%E4%BA%BA%E7%89%A9-%E7%99%BD%E8%A1%A3%E7%A7%80%E5%A3%AB-%E5%BD%B1%E7%A5%9E%E5%9B%BE"
  },
  {
    "name": "大圣残躯",
    "src": "%E4%BA%BA%E7%89%A9-%E5%A4%A7%E5%9C%A3%E6%AE%8B%E8%BA%AF-%E5%BD%B1%E7%A5%9E%E5%9B%BE"
  }
]
